{
  "devourer_hurt": {
    "subtitle": "sounds.legendfoxes.devourer_hurt",
    "sounds": [
      "legendfoxes:devourer_hurt"
    ]
  },
  "unbreakable_hurt": {
    "subtitle": "sounds.legendfoxes.unbreakable_hurt",
    "sounds": [
      "legendfoxes:unbreakable_hurt"
    ]
  },
  "devourer.idle1": {
    "subtitle": "sounds.legendfoxes.devourer.idle1",
    "sounds": [
      "legendfoxes:devourer.idle1"
    ]
  },
  "devourer.idle2": {
    "subtitle": "sounds.legendfoxes.devourer.idle2",
    "sounds": [
      "legendfoxes:devourer.idle2"
    ]
  },
  "devourer.idle3": {
    "subtitle": "sounds.legendfoxes.devourer.idle3",
    "sounds": [
      "legendfoxes:devourer.idle3"
    ]
  },
  "devourer.idle4": {
    "subtitle": "sounds.legendfoxes.devourer.idle4",
    "sounds": [
      "legendfoxes:devourer.idle4"
    ]
  },
  "devourer.idle5": {
    "subtitle": "sounds.legendfoxes.devourer.idle5",
    "sounds": [
      "legendfoxes:devourer.idle5"
    ]
  },
  "devourer.idle6": {
    "subtitle": "sounds.legendfoxes.devourer.idle6",
    "sounds": [
      "legendfoxes:devourer.idle6"
    ]
  },
  "devourer.idle7": {
    "subtitle": "sounds.legendfoxes.devourer.idle7",
    "sounds": [
      "legendfoxes:devourer.idle7"
    ]
  },
  "devourer.idle8": {
    "subtitle": "sounds.legendfoxes.devourer.idle8",
    "sounds": [
      "legendfoxes:devourer.idle8"
    ]
  },
  "devourer.idle9": {
    "subtitle": "sounds.legendfoxes.devourer.idle9",
    "sounds": [
      "legendfoxes:devourer.idle9"
    ]
  },
  "devourer_walk1": {
    "subtitle": "sounds.legendfoxes.devourer_walkq",
    "sounds": [
      "legendfoxes:devourer.devourer_walk1"
    ]
  },
  "devourer_walk2": {
    "subtitle": "sounds.legendfoxes.devourer_walk2",
    "sounds": [
      "legendfoxes:devourer.devourer_walk2"
    ]
  },
  "devourer_walk3": {
    "subtitle": "sounds.legendfoxes.devourer_walk3",
    "sounds": [
      "legendfoxes:devourer.devourer_walk3"
    ]
  },
  "devourer_walk4": {
    "subtitle": "sounds.legendfoxes.devourer_walk4",
    "sounds": [
      "legendfoxes:devourer.devourer_walk4"
    ]
  },
  "devourer_walk5": {
    "subtitle": "sounds.legendfoxes.devourer_walk5",
    "sounds": [
      "legendfoxes:devourer.devourer_walk5"
    ]
  },
  "devourer_walk6": {
    "subtitle": "sounds.legendfoxes.devourer_walk6",
    "sounds": [
      "legendfoxes:devourer.devourer_walk6"
    ]
  },
  "devourer_walk7": {
    "subtitle": "sounds.legendfoxes.devourer_walk7",
    "sounds": [
      "legendfoxes:devourer.devourer_walk7"
    ]
  },
  "devourer_walk8": {
    "subtitle": "sounds.legendfoxes.devourer_walk8",
    "sounds": [
      "legendfoxes:devourer.devourer_walk8"
    ]
  },
  "devourer_walk9": {
    "subtitle": "sounds.legendfoxes.devourer_walk9",
    "sounds": [
      "legendfoxes:devourer.devourer_walk9"
    ]
  },
  "devourer_walk10": {
    "subtitle": "sounds.legendfoxes.devourer_walk10",
    "sounds": [
      "legendfoxes:devourer.devourer_walk10"
    ]
  },
  "devourer_hurt1": {
    "subtitle": "sounds.legendfoxes.devourer_hurt1",
    "sounds": [
      "legendfoxes:devourer_hurt1"
    ]
  },
  "devourer_hurt2": {
    "subtitle": "sounds.legendfoxes.devourer_hurt2",
    "sounds": [
      "legendfoxes:devourer_hurt2"
    ]
  },
  "devourer_hurt3": {
    "subtitle": "sounds.legendfoxes.devourer_hurt3",
    "sounds": [
      "legendfoxes:devourer_hurt3"
    ]
  },
  "devourer_hurt4": {
    "subtitle": "sounds.legendfoxes.devourer_hurt4",
    "sounds": [
      "legendfoxes:devourer_hurt4"
    ]
  },
  "devourer_hurt5": {
    "subtitle": "sounds.legendfoxes.devourer_hurt5",
    "sounds": [
      "legendfoxes:devourer_hurt5"
    ]
  }
}